boson_multimodal/__init__.py
boson_multimodal/constants.py
boson_multimodal/data_types.py
boson_multimodal/audio_processing/higgs_audio_tokenizer.py
boson_multimodal/audio_processing/semantic_module.py
boson_multimodal/audio_processing/descriptaudiocodec/__init__.py
boson_multimodal/audio_processing/descriptaudiocodec/dac/model/base.py
boson_multimodal/audio_processing/descriptaudiocodec/dac/model/dac.py
boson_multimodal/audio_processing/descriptaudiocodec/dac/nn/layers.py
boson_multimodal/audio_processing/descriptaudiocodec/dac/nn/quantize.py
boson_multimodal/audio_processing/quantization/__init__.py
boson_multimodal/audio_processing/quantization/ac.py
boson_multimodal/audio_processing/quantization/core_vq.py
boson_multimodal/audio_processing/quantization/core_vq_lsx_version.py
boson_multimodal/audio_processing/quantization/ddp_utils.py
boson_multimodal/audio_processing/quantization/distrib.py
boson_multimodal/audio_processing/quantization/vq.py
boson_multimodal/data_collator/__init__.py
boson_multimodal/data_collator/higgs_audio_collator.py
boson_multimodal/dataset/__init__.py
boson_multimodal/dataset/chatml_dataset.py
boson_multimodal/model/__init__.py
boson_multimodal/model/higgs_audio/__init__.py
boson_multimodal/model/higgs_audio/audio_head.py
boson_multimodal/model/higgs_audio/common.py
boson_multimodal/model/higgs_audio/configuration_higgs_audio.py
boson_multimodal/model/higgs_audio/cuda_graph_runner.py
boson_multimodal/model/higgs_audio/custom_modules.py
boson_multimodal/model/higgs_audio/modeling_higgs_audio.py
boson_multimodal/model/higgs_audio/utils.py
boson_multimodal/serve/serve_engine.py
boson_multimodal/serve/utils.py
boson_multimodal-0.1.1.dist-info/licenses/LICENSE
boson_multimodal-0.1.1.dist-info/METADATA
boson_multimodal-0.1.1.dist-info/WHEEL
boson_multimodal-0.1.1.dist-info/top_level.txt
boson_multimodal-0.1.1.dist-info/RECORD
