Metadata-Version: 2.4
Name: boson_multimodal
Version: 0.1.1
Summary: Boson Multimodal - A multimodal AI framework
Home-page: https://github.com/yourusername/boson_multimodal
Author: Boson AI
Author-email: contact@boson-ai.com
Classifier: Programming Language :: Python :: 3
Classifier: License :: OSI Approved :: MIT License
Classifier: Operating System :: OS Independent
Requires-Python: >=3.8
License-File: LICENSE
Requires-Dist: descript-audio-codec
Requires-Dist: torch
Requires-Dist: transformers<4.47.0,>=4.45.1
Requires-Dist: librosa
Requires-Dist: dacite
Requires-Dist: boto3==1.35.36
Requires-Dist: s3fs
Requires-Dist: torchvision
Requires-Dist: torchaudio
Requires-Dist: json_repair
Requires-Dist: pandas
Requires-Dist: pydantic
Requires-Dist: vector_quantize_pytorch
Requires-Dist: loguru
Requires-Dist: pydub
Requires-Dist: ruff==0.12.2
Requires-Dist: omegaconf
Requires-Dist: click
Requires-Dist: langid
Requires-Dist: jieba
Requires-Dist: accelerate>=0.26.0
Dynamic: author
Dynamic: author-email
Dynamic: classifier
Dynamic: description
Dynamic: description-content-type
Dynamic: home-page
Dynamic: license-file
Dynamic: requires-dist
Dynamic: requires-python
Dynamic: summary
